[{"size": "2.5\u30a4\u30f3\u30c1", "capacity": "2TB", "interface": "SATA 3", "rpm": "5400", "thickness": "9.5mm", "dospara": {"value": 6323, "status": "\u5728\u5eab", "link": "//ck.jp.ap.valuecommerce.com/servlet/referral?sid=3450787&pid=886138595&vc_url=http%3A//www.dospara.co.jp/5shopping/detail_parts.php%3Fic%3D453537"}, "kakaku": {"value": 6323, "status": "\u4e0d\u660e", "link": "https://kakaku.com/item/K0001058986/"}, "amazon": {"value": 7590, "status": "\u5728\u5eab", "link": "https://www.amazon.co.jp/dp/B07DDCR787?tag=cjmarketing0a-22"}}]