[{"audio": "Realtek ALC S1200A", "chipset": "AMD B550", "crossfire": "\u25cb", "formfactor": "ATX", "max_memory": "128GB", "lan_speed": "10/100/1000/2500", "memory_slot": "4", "sata_slot": "6", "memory_type": "DIMM DDR4", "Socket": "SocketAM4", "dospara": {"value": 15390, "status": "\u5728\u5eab", "link": "//ck.jp.ap.valuecommerce.com/servlet/referral?sid=3450787&pid=886138595&vc_url=https%3A//www.dospara.co.jp/5shopping/detail_parts.php%3Fic%3D466996"}, "kakaku": {"value": 15390, "status": "\u4e0d\u660e", "link": "https://kakaku.com/item/K0001259409/"}, "sofmap": {"value": 15400, "status": "\u5728\u5eab", "link": "https://click.linksynergy.com/deeplink?id=q1VXjdL/3TY&mid=37641&murl=https%3A//www.sofmap.com/product_detail/exec/%3Fsku%3D20875773"}, "amazon": {"value": 15536, "status": "\u5728\u5eab", "link": "https://www.amazon.co.jp/dp/B089XXHY6K?tag=cjmarketing0a-22"}}]